jira2json/__init__.py
jira2json/__main__.py
jira2json-0.1.2.dist-info/LICENSE
jira2json-0.1.2.dist-info/METADATA
jira2json-0.1.2.dist-info/WHEEL
jira2json-0.1.2.dist-info/entry_points.txt
jira2json-0.1.2.dist-info/top_level.txt
jira2json-0.1.2.dist-info/RECORD
