Metadata-Version: 2.1
Name: jira2json
Version: 0.1.2
Summary: Dump JIRA issues to a dictionary / JSON.
Home-page: https://github.com/bharel/jira_to_json
Download-URL: https://pypi.org/project/jira2json/#files
Author: Bar Harel
Maintainer: Bar Harel
License: MIT License
Classifier: Development Status :: 3 - Alpha
Classifier: Environment :: Console
Classifier: Intended Audience :: Developers
Classifier: Intended Audience :: Information Technology
Classifier: License :: OSI Approved :: MIT License
Classifier: Operating System :: OS Independent
Classifier: Programming Language :: Python :: 3
Classifier: Topic :: Internet :: WWW/HTTP :: Site Management
Classifier: Topic :: Software Development :: Bug Tracking
Classifier: Typing :: Typed
License-File: LICENSE
Requires-Dist: requests (~=2.30)
Provides-Extra: dev
Requires-Dist: types-requests ; extra == 'dev'
Requires-Dist: coverage ; extra == 'dev'
Provides-Extra: dotenv
Requires-Dist: python-dotenv ; extra == 'dotenv'
